Metadata-Version: 2.1
Name: django-mp-notify
Version: 1.0.0
Summary: Django admin app
Home-page: https://github.com/pmaigutyak/mp-notify
Download-URL: https://github.com/pmaigutyak/mp-notify/archive/1.0.0.tar.gz
Author: Paul Maigutyak
Author-email: pmaigutyak@gmail.com
License: MIT
License-File: LICENSE
